Metadata-Version: 1.0
Name: lda2vec
Version: 0.16.10
Summary: Tools for interpreting natural language
Home-page: UNKNOWN
Author: Nathan Raw
Author-email: nxr9266@rit.edu
License: UNKNOWN
Platform: UNKNOWN
